{
  "totalResults": 17328,
  "searchResults": [
    {
      "lexicality": 0,
      "count": 139,
      "word": "half-god"
    },
    {
      "lexicality": 0,
      "count": 139,
      "word": "apprises"
    },
    {
      "lexicality": 0,
      "count": 139,
      "word": "scragged"
    },
    {
      "lexicality": 0,
      "count": 139,
      "word": "foraying"
    },
    {
      "lexicality": 0,
      "count": 139,
      "word": "Salishan"
    },
    {
      "lexicality": 0,
      "count": 139,
      "word": "Huallaga"
    },
    {
      "lexicality": 0,
      "count": 139,
      "word": "castanet"
    },
    {
      "lexicality": 0,
      "count": 139,
      "word": "abseiled"
    },
    {
      "lexicality": 0,
      "count": 139,
      "word": "outraise"
    },
    {
      "lexicality": 0,
      "count": 139,
      "word": "vitalist"
    },
    {
      "lexicality": 0,
      "count": 139,
      "word": "sub-rosa"
    },
    {
      "lexicality": 0,
      "count": 139,
      "word": "tachyons"
    },
    {
      "lexicality": 0,
      "count": 139,
      "word": "giftable"
    },
    {
      "lexicality": 0,
      "count": 139,
      "word": "novation"
    },
    {
      "lexicality": 0,
      "count": 139,
      "word": "potables"
    },
    {
      "lexicality": 0,
      "count": 139,
      "word": "dentally"
    },
    {
      "lexicality": 0,
      "count": 139,
      "word": "butyrate"
    },
    {
      "lexicality": 0,
      "count": 139,
      "word": "muscatel"
    },
    {
      "lexicality": 0,
      "count": 139,
      "word": "chelated"
    },
    {
      "lexicality": 0,
      "count": 139,
      "word": "catbirds"
    },
    {
      "lexicality": 0,
      "count": 139,
      "word": "freesias"
    },
    {
      "lexicality": 0,
      "count": 139,
      "word": "terrasse"
    },
    {
      "lexicality": 0,
      "count": 139,
      "word": "caterans"
    },
    {
      "lexicality": 0,
      "count": 139,
      "word": "cablecos"
    },
    {
      "lexicality": 0,
      "count": 138,
      "word": "jacinths"
    },
    {
      "lexicality": 0,
      "count": 138,
      "word": "valiancy"
    },
    {
      "lexicality": 0,
      "count": 138,
      "word": "votaress"
    },
    {
      "lexicality": 0,
      "count": 138,
      "word": "Eastmain"
    },
    {
      "lexicality": 0,
      "count": 138,
      "word": "pay-dirt"
    },
    {
      "lexicality": 0,
      "count": 138,
      "word": "maréchal"
    },
    {
      "lexicality": 0,
      "count": 138,
      "word": "abutters"
    },
    {
      "lexicality": 0,
      "count": 138,
      "word": "asperger"
    },
    {
      "lexicality": 0,
      "count": 138,
      "word": "Pullmans"
    },
    {
      "lexicality": 0,
      "count": 138,
      "word": "coronate"
    },
    {
      "lexicality": 0,
      "count": 138,
      "word": "samovars"
    },
    {
      "lexicality": 0,
      "count": 138,
      "word": "retablos"
    },
    {
      "lexicality": 0,
      "count": 138,
      "word": "avantage"
    },
    {
      "lexicality": 0,
      "count": 138,
      "word": "sagamore"
    },
    {
      "lexicality": 0,
      "count": 138,
      "word": "batarang"
    },
    {
      "lexicality": 0,
      "count": 138,
      "word": "rerating"
    },
    {
      "lexicality": 0,
      "count": 138,
      "word": "taverner"
    },
    {
      "lexicality": 0,
      "count": 138,
      "word": "Arameans"
    },
    {
      "lexicality": 0,
      "count": 138,
      "word": "cheddars"
    },
    {
      "lexicality": 0,
      "count": 138,
      "word": "taleggio"
    },
    {
      "lexicality": 0,
      "count": 138,
      "word": "Sasanian"
    },
    {
      "lexicality": 0,
      "count": 138,
      "word": "hushabye"
    },
    {
      "lexicality": 0,
      "count": 137,
      "word": "shikaree"
    },
    {
      "lexicality": 0,
      "count": 137,
      "word": "chantant"
    },
    {
      "lexicality": 0,
      "count": 137,
      "word": "kampongs"
    },
    {
      "lexicality": 0,
      "count": 137,
      "word": "transire"
    },
    {
      "lexicality": 0,
      "count": 137,
      "word": "Lazarist"
    },
    {
      "lexicality": 0,
      "count": 137,
      "word": "furfural"
    },
    {
      "lexicality": 0,
      "count": 137,
      "word": "tyrannie"
    },
    {
      "lexicality": 0,
      "count": 137,
      "word": "vaporing"
    },
    {
      "lexicality": 0,
      "count": 137,
      "word": "Malayali"
    },
    {
      "lexicality": 0,
      "count": 137,
      "word": "gracioso"
    },
    {
      "lexicality": 0,
      "count": 137,
      "word": "alpinism"
    },
    {
      "lexicality": 0,
      "count": 137,
      "word": "palavers"
    },
    {
      "lexicality": 0,
      "count": 137,
      "word": "man-mark"
    },
    {
      "lexicality": 0,
      "count": 137,
      "word": "non-auto"
    },
    {
      "lexicality": 0,
      "count": 137,
      "word": "hair-dye"
    },
    {
      "lexicality": 0,
      "count": 137,
      "word": "tarlatan"
    },
    {
      "lexicality": 0,
      "count": 137,
      "word": "satiates"
    },
    {
      "lexicality": 0,
      "count": 137,
      "word": "Alma-Ata"
    },
    {
      "lexicality": 0,
      "count": 137,
      "word": "chinaman"
    },
    {
      "lexicality": 0,
      "count": 137,
      "word": "démarche"
    },
    {
      "lexicality": 0,
      "count": 137,
      "word": "Shar-Pei"
    },
    {
      "lexicality": 0,
      "count": 137,
      "word": "headways"
    },
    {
      "lexicality": 0,
      "count": 137,
      "word": "Malenkov"
    },
    {
      "lexicality": 0,
      "count": 137,
      "word": "aborning"
    },
    {
      "lexicality": 0,
      "count": 137,
      "word": "rescaled"
    },
    {
      "lexicality": 0,
      "count": 137,
      "word": "Ali Baba"
    },
    {
      "lexicality": 0,
      "count": 136,
      "word": "ha'pence"
    },
    {
      "lexicality": 0,
      "count": 136,
      "word": "abbatial"
    },
    {
      "lexicality": 0,
      "count": 136,
      "word": "postages"
    },
    {
      "lexicality": 0,
      "count": 136,
      "word": "carabaos"
    },
    {
      "lexicality": 0,
      "count": 136,
      "word": "backbite"
    },
    {
      "lexicality": 0,
      "count": 136,
      "word": "Cattleya"
    },
    {
      "lexicality": 0,
      "count": 136,
      "word": "Madalene"
    },
    {
      "lexicality": 0,
      "count": 136,
      "word": "Al-Qabas"
    },
    {
      "lexicality": 0,
      "count": 136,
      "word": "blacktip"
    },
    {
      "lexicality": 0,
      "count": 136,
      "word": "slavered"
    },
    {
      "lexicality": 0,
      "count": 136,
      "word": "respawns"
    },
    {
      "lexicality": 0,
      "count": 136,
      "word": "ciliates"
    },
    {
      "lexicality": 0,
      "count": 136,
      "word": "sauciest"
    },
    {
      "lexicality": 0,
      "count": 136,
      "word": "spandrel"
    },
    {
      "lexicality": 0,
      "count": 136,
      "word": "recapper"
    },
    {
      "lexicality": 0,
      "count": 136,
      "word": "unflawed"
    },
    {
      "lexicality": 0,
      "count": 136,
      "word": "ignorami"
    },
    {
      "lexicality": 0,
      "count": 136,
      "word": "humanure"
    },
    {
      "lexicality": 0,
      "count": 136,
      "word": "catsuits"
    },
    {
      "lexicality": 0,
      "count": 136,
      "word": "pétanque"
    },
    {
      "lexicality": 0,
      "count": 136,
      "word": "brandade"
    },
    {
      "lexicality": 0,
      "count": 136,
      "word": "Babbitts"
    },
    {
      "lexicality": 0,
      "count": 135,
      "word": "legatine"
    },
    {
      "lexicality": 0,
      "count": 135,
      "word": "slatting"
    },
    {
      "lexicality": 0,
      "count": 135,
      "word": "Kaiserin"
    },
    {
      "lexicality": 0,
      "count": 135,
      "word": "dyspnoea"
    },
    {
      "lexicality": 0,
      "count": 135,
      "word": "quintain"
    },
    {
      "lexicality": 0,
      "count": 135,
      "word": "waviness"
    },
    {
      "lexicality": 0,
      "count": 135,
      "word": "Colossae"
    },
    {
      "lexicality": 0,
      "count": 135,
      "word": "cabooses"
    },
    {
      "lexicality": 0,
      "count": 135,
      "word": "coracles"
    },
    {
      "lexicality": 0,
      "count": 135,
      "word": "danglers"
    },
    {
      "lexicality": 0,
      "count": 135,
      "word": "coupable"
    },
    {
      "lexicality": 0,
      "count": 135,
      "word": "loyalism"
    },
    {
      "lexicality": 0,
      "count": 135,
      "word": "assister"
    },
    {
      "lexicality": 0,
      "count": 135,
      "word": "kemosabe"
    },
    {
      "lexicality": 0,
      "count": 135,
      "word": "catchily"
    },
    {
      "lexicality": 0,
      "count": 135,
      "word": "napalmed"
    },
    {
      "lexicality": 0,
      "count": 135,
      "word": "flattops"
    },
    {
      "lexicality": 0,
      "count": 135,
      "word": "Sogdians"
    },
    {
      "lexicality": 0,
      "count": 134,
      "word": "decretal"
    },
    {
      "lexicality": 0,
      "count": 134,
      "word": "laugheth"
    },
    {
      "lexicality": 0,
      "count": 134,
      "word": "deranges"
    },
    {
      "lexicality": 0,
      "count": 134,
      "word": "sophical"
    },
    {
      "lexicality": 0,
      "count": 134,
      "word": "Laureles"
    },
    {
      "lexicality": 0,
      "count": 134,
      "word": "lead-lap"
    },
    {
      "lexicality": 0,
      "count": 134,
      "word": "rake-off"
    },
    {
      "lexicality": 0,
      "count": 134,
      "word": "andesite"
    },
    {
      "lexicality": 0,
      "count": 134,
      "word": "airdrome"
    },
    {
      "lexicality": 0,
      "count": 134,
      "word": "tee-ball"
    },
    {
      "lexicality": 0,
      "count": 134,
      "word": "airshaft"
    },
    {
      "lexicality": 0,
      "count": 134,
      "word": "aglitter"
    },
    {
      "lexicality": 0,
      "count": 134,
      "word": "dropback"
    },
    {
      "lexicality": 0,
      "count": 134,
      "word": "urbanize"
    },
    {
      "lexicality": 0,
      "count": 134,
      "word": "iron-man"
    },
    {
      "lexicality": 0,
      "count": 134,
      "word": "baclofen"
    },
    {
      "lexicality": 0,
      "count": 134,
      "word": "champeen"
    },
    {
      "lexicality": 0,
      "count": 133,
      "word": "granteth"
    },
    {
      "lexicality": 0,
      "count": 133,
      "word": "sea-fish"
    },
    {
      "lexicality": 0,
      "count": 133,
      "word": "bereaves"
    },
    {
      "lexicality": 0,
      "count": 133,
      "word": "standish"
    },
    {
      "lexicality": 0,
      "count": 133,
      "word": "Pasiphae"
    },
    {
      "lexicality": 0,
      "count": 133,
      "word": "Maeander"
    },
    {
      "lexicality": 0,
      "count": 133,
      "word": "procaine"
    },
    {
      "lexicality": 0,
      "count": 133,
      "word": "Klaipeda"
    },
    {
      "lexicality": 0,
      "count": 133,
      "word": "vamoosed"
    },
    {
      "lexicality": 0,
      "count": 133,
      "word": "rollable"
    },
    {
      "lexicality": 0,
      "count": 133,
      "word": "killable"
    },
    {
      "lexicality": 0,
      "count": 133,
      "word": "manouvre"
    },
    {
      "lexicality": 0,
      "count": 133,
      "word": "lalalala"
    },
    {
      "lexicality": 0,
      "count": 133,
      "word": "viridian"
    },
    {
      "lexicality": 0,
      "count": 133,
      "word": "landrush"
    },
    {
      "lexicality": 0,
      "count": 133,
      "word": "nutation"
    },
    {
      "lexicality": 0,
      "count": 133,
      "word": "spackled"
    },
    {
      "lexicality": 0,
      "count": 133,
      "word": "waiflike"
    },
    {
      "lexicality": 0,
      "count": 133,
      "word": "endpaper"
    },
    {
      "lexicality": 0,
      "count": 133,
      "word": "labmates"
    },
    {
      "lexicality": 0,
      "count": 133,
      "word": "attaboys"
    },
    {
      "lexicality": 0,
      "count": 132,
      "word": "examin'd"
    },
    {
      "lexicality": 0,
      "count": 132,
      "word": "aspheric"
    },
    {
      "lexicality": 0,
      "count": 132,
      "word": "wouldnae"
    },
    {
      "lexicality": 0,
      "count": 132,
      "word": "Turcoman"
    },
    {
      "lexicality": 0,
      "count": 132,
      "word": "tarandus"
    },
    {
      "lexicality": 0,
      "count": 132,
      "word": "planless"
    },
    {
      "lexicality": 0,
      "count": 132,
      "word": "quinella"
    },
    {
      "lexicality": 0,
      "count": 132,
      "word": "jalousie"
    },
    {
      "lexicality": 0,
      "count": 132,
      "word": "airtimes"
    },
    {
      "lexicality": 0,
      "count": 132,
      "word": "victrola"
    },
    {
      "lexicality": 0,
      "count": 132,
      "word": "esterase"
    },
    {
      "lexicality": 0,
      "count": 132,
      "word": "die-back"
    },
    {
      "lexicality": 0,
      "count": 132,
      "word": "freegans"
    },
    {
      "lexicality": 0,
      "count": 132,
      "word": "fauxhawk"
    },
    {
      "lexicality": 0,
      "count": 132,
      "word": "dungheap"
    },
    {
      "lexicality": 0,
      "count": 132,
      "word": "stargaze"
    },
    {
      "lexicality": 0,
      "count": 132,
      "word": "palmitic"
    },
    {
      "lexicality": 0,
      "count": 132,
      "word": "nonlegal"
    },
    {
      "lexicality": 0,
      "count": 132,
      "word": "drabbles"
    },
    {
      "lexicality": 0,
      "count": 132,
      "word": "Kattegat"
    },
    {
      "lexicality": 0,
      "count": 131,
      "word": "gonfalon"
    },
    {
      "lexicality": 0,
      "count": 131,
      "word": "milk-can"
    },
    {
      "lexicality": 0,
      "count": 131,
      "word": "Fatimite"
    },
    {
      "lexicality": 0,
      "count": 131,
      "word": "sarcenet"
    },
    {
      "lexicality": 0,
      "count": 131,
      "word": "Castagno"
    },
    {
      "lexicality": 0,
      "count": 131,
      "word": "goalball"
    },
    {
      "lexicality": 0,
      "count": 131,
      "word": "anaphase"
    },
    {
      "lexicality": 0,
      "count": 131,
      "word": "chessman"
    },
    {
      "lexicality": 0,
      "count": 131,
      "word": "Ruthenia"
    },
    {
      "lexicality": 0,
      "count": 131,
      "word": "smartish"
    },
    {
      "lexicality": 0,
      "count": 131,
      "word": "treadles"
    },
    {
      "lexicality": 0,
      "count": 131,
      "word": "big-head"
    },
    {
      "lexicality": 0,
      "count": 131,
      "word": "piss-ant"
    },
    {
      "lexicality": 0,
      "count": 131,
      "word": "revelant"
    },
    {
      "lexicality": 0,
      "count": 131,
      "word": "facilely"
    },
    {
      "lexicality": 0,
      "count": 131,
      "word": "pawprint"
    },
    {
      "lexicality": 0,
      "count": 131,
      "word": "aiguille"
    },
    {
      "lexicality": 0,
      "count": 131,
      "word": "brainbox"
    },
    {
      "lexicality": 0,
      "count": 131,
      "word": "alizarin"
    },
    {
      "lexicality": 0,
      "count": 131,
      "word": "biriyani"
    },
    {
      "lexicality": 0,
      "count": 131,
      "word": "dearborn"
    },
    {
      "lexicality": 0,
      "count": 131,
      "word": "pardoner"
    },
    {
      "lexicality": 0,
      "count": 131,
      "word": "jackhole"
    },
    {
      "lexicality": 0,
      "count": 130,
      "word": "lingular"
    },
    {
      "lexicality": 0,
      "count": 130,
      "word": "dispread"
    },
    {
      "lexicality": 0,
      "count": 130,
      "word": "bandsman"
    },
    {
      "lexicality": 0,
      "count": 130,
      "word": "lamellar"
    },
    {
      "lexicality": 0,
      "count": 130,
      "word": "paginate"
    },
    {
      "lexicality": 0,
      "count": 130,
      "word": "palmated"
    },
    {
      "lexicality": 0,
      "count": 130,
      "word": "telecare"
    },
    {
      "lexicality": 0,
      "count": 130,
      "word": "yardages"
    },
    {
      "lexicality": 0,
      "count": 130,
      "word": "deathray"
    },
    {
      "lexicality": 0,
      "count": 130,
      "word": "verdancy"
    },
    {
      "lexicality": 0,
      "count": 130,
      "word": "wackadoo"
    },
    {
      "lexicality": 0,
      "count": 130,
      "word": "crayoned"
    },
    {
      "lexicality": 0,
      "count": 130,
      "word": "Saxonism"
    },
    {
      "lexicality": 0,
      "count": 130,
      "word": "Apaporis"
    },
    {
      "lexicality": 0,
      "count": 129,
      "word": "assessee"
    },
    {
      "lexicality": 0,
      "count": 129,
      "word": "Aramaean"
    },
    {
      "lexicality": 0,
      "count": 129,
      "word": "seedsman"
    },
    {
      "lexicality": 0,
      "count": 129,
      "word": "nocturia"
    },
    {
      "lexicality": 0,
      "count": 129,
      "word": "defamers"
    },
    {
      "lexicality": 0,
      "count": 129,
      "word": "diluvian"
    },
    {
      "lexicality": 0,
      "count": 129,
      "word": "ransacks"
    },
    {
      "lexicality": 0,
      "count": 129,
      "word": "intaking"
    },
    {
      "lexicality": 0,
      "count": 129,
      "word": "valuator"
    },
    {
      "lexicality": 0,
      "count": 129,
      "word": "man-hour"
    },
    {
      "lexicality": 0,
      "count": 129,
      "word": "offramps"
    },
    {
      "lexicality": 0,
      "count": 129,
      "word": "borracho"
    },
    {
      "lexicality": 0,
      "count": 129,
      "word": "candling"
    },
    {
      "lexicality": 0,
      "count": 129,
      "word": "chiminea"
    },
    {
      "lexicality": 0,
      "count": 129,
      "word": "Narnians"
    },
    {
      "lexicality": 0,
      "count": 129,
      "word": "hearting"
    },
    {
      "lexicality": 0,
      "count": 129,
      "word": "apiaries"
    },
    {
      "lexicality": 0,
      "count": 129,
      "word": "velveeta"
    },
    {
      "lexicality": 0,
      "count": 129,
      "word": "fratboys"
    },
    {
      "lexicality": 0,
      "count": 129,
      "word": "spawners"
    },
    {
      "lexicality": 0,
      "count": 129,
      "word": "satsumas"
    },
    {
      "lexicality": 0,
      "count": 129,
      "word": "chordate"
    },
    {
      "lexicality": 0,
      "count": 129,
      "word": "Mid East"
    },
    {
      "lexicality": 0,
      "count": 129,
      "word": "Itzcoatl"
    },
    {
      "lexicality": 0,
      "count": 128,
      "word": "hay-cart"
    },
    {
      "lexicality": 0,
      "count": 128,
      "word": "unheaded"
    },
    {
      "lexicality": 0,
      "count": 128,
      "word": "Illimani"
    },
    {
      "lexicality": 0,
      "count": 128,
      "word": "Cyprians"
    },
    {
      "lexicality": 0,
      "count": 128,
      "word": "Umbrians"
    },
    {
      "lexicality": 0,
      "count": 128,
      "word": "ansibles"
    },
    {
      "lexicality": 0,
      "count": 128,
      "word": "ordinals"
    },
    {
      "lexicality": 0,
      "count": 128,
      "word": "flatfoot"
    },
    {
      "lexicality": 0,
      "count": 128,
      "word": "cabriole"
    },
    {
      "lexicality": 0,
      "count": 128,
      "word": "gramercy"
    },
    {
      "lexicality": 0,
      "count": 128,
      "word": "comparer"
    },
    {
      "lexicality": 0,
      "count": 128,
      "word": "sandspit"
    },
    {
      "lexicality": 0,
      "count": 128,
      "word": "flyaways"
    },
    {
      "lexicality": 0,
      "count": 128,
      "word": "tealight"
    },
    {
      "lexicality": 0,
      "count": 128,
      "word": "heuchera"
    },
    {
      "lexicality": 0,
      "count": 128,
      "word": "flatting"
    },
    {
      "lexicality": 0,
      "count": 127,
      "word": "carberry"
    },
    {
      "lexicality": 0,
      "count": 127,
      "word": "perizoma"
    },
    {
      "lexicality": 0,
      "count": 127,
      "word": "Gavarnie"
    },
    {
      "lexicality": 0,
      "count": 127,
      "word": "superadd"
    },
    {
      "lexicality": 0,
      "count": 127,
      "word": "marchesa"
    },
    {
      "lexicality": 0,
      "count": 127,
      "word": "jubilate"
    },
    {
      "lexicality": 0,
      "count": 127,
      "word": "Marranos"
    },
    {
      "lexicality": 0,
      "count": 127,
      "word": "calderon"
    },
    {
      "lexicality": 0,
      "count": 127,
      "word": "chappals"
    },
    {
      "lexicality": 0,
      "count": 127,
      "word": "sackless"
    },
    {
      "lexicality": 0,
      "count": 127,
      "word": "overleaf"
    },
    {
      "lexicality": 0,
      "count": 127,
      "word": "monachus"
    },
    {
      "lexicality": 0,
      "count": 127,
      "word": "autogyro"
    },
    {
      "lexicality": 0,
      "count": 127,
      "word": "slalomed"
    },
    {
      "lexicality": 0,
      "count": 127,
      "word": "valproic"
    },
    {
      "lexicality": 0,
      "count": 127,
      "word": "baldhead"
    },
    {
      "lexicality": 0,
      "count": 127,
      "word": "blueback"
    },
    {
      "lexicality": 0,
      "count": 126,
      "word": "acquir'd"
    },
    {
      "lexicality": 0,
      "count": 126,
      "word": "tipstaff"
    },
    {
      "lexicality": 0,
      "count": 126,
      "word": "tattlers"
    },
    {
      "lexicality": 0,
      "count": 126,
      "word": "dracaena"
    },
    {
      "lexicality": 0,
      "count": 126,
      "word": "Venerian"
    },
    {
      "lexicality": 0,
      "count": 126,
      "word": "cheaping"
    },
    {
      "lexicality": 0,
      "count": 126,
      "word": "flashgun"
    },
    {
      "lexicality": 0,
      "count": 126,
      "word": "tapdance"
    },
    {
      "lexicality": 0,
      "count": 126,
      "word": "saucepot"
    },
    {
      "lexicality": 0,
      "count": 126,
      "word": "sweatily"
    },
    {
      "lexicality": 0,
      "count": 126,
      "word": "cardoons"
    },
    {
      "lexicality": 0,
      "count": 126,
      "word": "broasted"
    },
    {
      "lexicality": 0,
      "count": 126,
      "word": "glamping"
    },
    {
      "lexicality": 0,
      "count": 125,
      "word": "prelatic"
    },
    {
      "lexicality": 0,
      "count": 125,
      "word": "innating"
    },
    {
      "lexicality": 0,
      "count": 125,
      "word": "savegame"
    },
    {
      "lexicality": 0,
      "count": 125,
      "word": "vocality"
    },
    {
      "lexicality": 0,
      "count": 125,
      "word": "somalian"
    },
    {
      "lexicality": 0,
      "count": 125,
      "word": "yardarms"
    },
    {
      "lexicality": 0,
      "count": 125,
      "word": "blatting"
    },
    {
      "lexicality": 0,
      "count": 125,
      "word": "caviling"
    },
    {
      "lexicality": 0,
      "count": 125,
      "word": "reteamed"
    },
    {
      "lexicality": 0,
      "count": 125,
      "word": "Sardegna"
    },
    {
      "lexicality": 0,
      "count": 125,
      "word": "proposta"
    },
    {
      "lexicality": 0,
      "count": 125,
      "word": "framings"
    },
    {
      "lexicality": 0,
      "count": 125,
      "word": "barrista"
    },
    {
      "lexicality": 0,
      "count": 125,
      "word": "megahits"
    },
    {
      "lexicality": 0,
      "count": 125,
      "word": "chitarra"
    },
    {
      "lexicality": 0,
      "count": 125,
      "word": "gaminess"
    },
    {
      "lexicality": 0,
      "count": 124,
      "word": "coronach"
    },
    {
      "lexicality": 0,
      "count": 124,
      "word": "unwashen"
    },
    {
      "lexicality": 0,
      "count": 124,
      "word": "nitrated"
    },
    {
      "lexicality": 0,
      "count": 124,
      "word": "autohide"
    },
    {
      "lexicality": 0,
      "count": 124,
      "word": "Vesuvian"
    },
    {
      "lexicality": 0,
      "count": 124,
      "word": "probates"
    },
    {
      "lexicality": 0,
      "count": 124,
      "word": "pallidum"
    },
    {
      "lexicality": 0,
      "count": 124,
      "word": "engraves"
    },
    {
      "lexicality": 0,
      "count": 124,
      "word": "harakiri"
    },
    {
      "lexicality": 0,
      "count": 124,
      "word": "valuably"
    },
    {
      "lexicality": 0,
      "count": 124,
      "word": "trayless"
    },
    {
      "lexicality": 0,
      "count": 124,
      "word": "toasties"
    },
    {
      "lexicality": 0,
      "count": 124,
      "word": "clafouti"
    },
    {
      "lexicality": 0,
      "count": 124,
      "word": "artboard"
    },
    {
      "lexicality": 0,
      "count": 123,
      "word": "tetramer"
    },
    {
      "lexicality": 0,
      "count": 123,
      "word": "puggaree"
    },
    {
      "lexicality": 0,
      "count": 123,
      "word": "coagulum"
    },
    {
      "lexicality": 0,
      "count": 123,
      "word": "cavatina"
    },
    {
      "lexicality": 0,
      "count": 123,
      "word": "venation"
    },
    {
      "lexicality": 0,
      "count": 123,
      "word": "cat-back"
    },
    {
      "lexicality": 0,
      "count": 123,
      "word": "Pantazis"
    },
    {
      "lexicality": 0,
      "count": 123,
      "word": "salients"
    },
    {
      "lexicality": 0,
      "count": 123,
      "word": "Danegeld"
    },
    {
      "lexicality": 0,
      "count": 123,
      "word": "saccades"
    },
    {
      "lexicality": 0,
      "count": 123,
      "word": "preparin"
    },
    {
      "lexicality": 0,
      "count": 123,
      "word": "half-ape"
    },
    {
      "lexicality": 0,
      "count": 123,
      "word": "cableway"
    },
    {
      "lexicality": 0,
      "count": 123,
      "word": "wordmark"
    },
    {
      "lexicality": 0,
      "count": 123,
      "word": "minimart"
    },
    {
      "lexicality": 0,
      "count": 123,
      "word": "tagatose"
    },
    {
      "lexicality": 0,
      "count": 123,
      "word": "lasagnas"
    },
    {
      "lexicality": 0,
      "count": 123,
      "word": "wearings"
    },
    {
      "lexicality": 0,
      "count": 123,
      "word": "Booleans"
    },
    {
      "lexicality": 0,
      "count": 122,
      "word": "fraudful"
    },
    {
      "lexicality": 0,
      "count": 122,
      "word": "ayudante"
    },
    {
      "lexicality": 0,
      "count": 122,
      "word": "ramifies"
    },
    {
      "lexicality": 0,
      "count": 122,
      "word": "craplets"
    },
    {
      "lexicality": 0,
      "count": 122,
      "word": "canonise"
    },
    {
      "lexicality": 0,
      "count": 122,
      "word": "branders"
    },
    {
      "lexicality": 0,
      "count": 122,
      "word": "toe-nail"
    },
    {
      "lexicality": 0,
      "count": 122,
      "word": "paniscus"
    },
    {
      "lexicality": 0,
      "count": 122,
      "word": "jailable"
    },
    {
      "lexicality": 0,
      "count": 122,
      "word": "patriate"
    },
    {
      "lexicality": 0,
      "count": 122,
      "word": "fatheads"
    },
    {
      "lexicality": 0,
      "count": 122,
      "word": "playsuit"
    },
    {
      "lexicality": 0,
      "count": 122,
      "word": "batwings"
    },
    {
      "lexicality": 0,
      "count": 122,
      "word": "bolivian"
    },
    {
      "lexicality": 0,
      "count": 122,
      "word": "anti-art"
    },
    {
      "lexicality": 0,
      "count": 122,
      "word": "chattier"
    },
    {
      "lexicality": 0,
      "count": 122,
      "word": "sweatier"
    },
    {
      "lexicality": 0,
      "count": 122,
      "word": "Sahrawis"
    },
    {
      "lexicality": 0,
      "count": 122,
      "word": "bottarga"
    },
    {
      "lexicality": 0,
      "count": 121,
      "word": "aunswere"
    },
    {
      "lexicality": 0,
      "count": 121,
      "word": "laudator"
    },
    {
      "lexicality": 0,
      "count": 121,
      "word": "forelady"
    },
    {
      "lexicality": 0,
      "count": 121,
      "word": "titulars"
    },
    {
      "lexicality": 0,
      "count": 121,
      "word": "statedly"
    },
    {
      "lexicality": 0,
      "count": 121,
      "word": "anthropo"
    },
    {
      "lexicality": 0,
      "count": 121,
      "word": "exigeant"
    },
    {
      "lexicality": 0,
      "count": 121,
      "word": "pulvinar"
    },
    {
      "lexicality": 0,
      "count": 121,
      "word": "tuneable"
    },
    {
      "lexicality": 0,
      "count": 121,
      "word": "deejayed"
    },
    {
      "lexicality": 0,
      "count": 121,
      "word": "Taconite"
    },
    {
      "lexicality": 0,
      "count": 121,
      "word": "boybands"
    },
    {
      "lexicality": 0,
      "count": 121,
      "word": "adulated"
    },
    {
      "lexicality": 0,
      "count": 121,
      "word": "fattiest"
    },
    {
      "lexicality": 0,
      "count": 121,
      "word": "Dicentra"
    },
    {
      "lexicality": 0,
      "count": 121,
      "word": "Tauruses"
    },
    {
      "lexicality": 0,
      "count": 121,
      "word": "apiarist"
    },
    {
      "lexicality": 0,
      "count": 121,
      "word": "signator"
    },
    {
      "lexicality": 0,
      "count": 120,
      "word": "archaics"
    },
    {
      "lexicality": 0,
      "count": 120,
      "word": "climatal"
    },
    {
      "lexicality": 0,
      "count": 120,
      "word": "jaghires"
    },
    {
      "lexicality": 0,
      "count": 120,
      "word": "yataghan"
    },
    {
      "lexicality": 0,
      "count": 120,
      "word": "charales"
    },
    {
      "lexicality": 0,
      "count": 120,
      "word": "Fedzilla"
    },
    {
      "lexicality": 0,
      "count": 120,
      "word": "armyworm"
    },
    {
      "lexicality": 0,
      "count": 120,
      "word": "berbatov"
    },
    {
      "lexicality": 0,
      "count": 120,
      "word": "pallidly"
    },
    {
      "lexicality": 0,
      "count": 120,
      "word": "cozenage"
    },
    {
      "lexicality": 0,
      "count": 120,
      "word": "medaling"
    },
    {
      "lexicality": 0,
      "count": 120,
      "word": "Sealyham"
    },
    {
      "lexicality": 0,
      "count": 120,
      "word": "laywoman"
    },
    {
      "lexicality": 0,
      "count": 120,
      "word": "fatlings"
    },
    {
      "lexicality": 0,
      "count": 120,
      "word": "Nabatean"
    },
    {
      "lexicality": 0,
      "count": 120,
      "word": "blatancy"
    },
    {
      "lexicality": 0,
      "count": 120,
      "word": "manboobs"
    },
    {
      "lexicality": 0,
      "count": 120,
      "word": "plebians"
    },
    {
      "lexicality": 0,
      "count": 120,
      "word": "rainwear"
    },
    {
      "lexicality": 0,
      "count": 120,
      "word": "foldaway"
    },
    {
      "lexicality": 0,
      "count": 120,
      "word": "backload"
    },
    {
      "lexicality": 0,
      "count": 119,
      "word": "sumpitan"
    },
    {
      "lexicality": 0,
      "count": 119,
      "word": "Karditsa"
    },
    {
      "lexicality": 0,
      "count": 119,
      "word": "Viramune"
    },
    {
      "lexicality": 0,
      "count": 119,
      "word": "updation"
    },
    {
      "lexicality": 0,
      "count": 119,
      "word": "ensilage"
    },
    {
      "lexicality": 0,
      "count": 119,
      "word": "quadriga"
    },
    {
      "lexicality": 0,
      "count": 119,
      "word": "enthrals"
    },
    {
      "lexicality": 0,
      "count": 119,
      "word": "rockaway"
    },
    {
      "lexicality": 0,
      "count": 119,
      "word": "pronator"
    },
    {
      "lexicality": 0,
      "count": 119,
      "word": "pleadeth"
    },
    {
      "lexicality": 0,
      "count": 119,
      "word": "ballades"
    },
    {
      "lexicality": 0,
      "count": 119,
      "word": "cambered"
    },
    {
      "lexicality": 0,
      "count": 119,
      "word": "Coates's"
    },
    {
      "lexicality": 0,
      "count": 119,
      "word": "cyanogen"
    },
    {
      "lexicality": 0,
      "count": 119,
      "word": "seatrout"
    },
    {
      "lexicality": 0,
      "count": 119,
      "word": "elatedly"
    },
    {
      "lexicality": 0,
      "count": 119,
      "word": "ladyfish"
    },
    {
      "lexicality": 0,
      "count": 119,
      "word": "frontals"
    },
    {
      "lexicality": 0,
      "count": 119,
      "word": "crammers"
    },
    {
      "lexicality": 0,
      "count": 119,
      "word": "Rombauer"
    },
    {
      "lexicality": 0,
      "count": 119,
      "word": "missable"
    },
    {
      "lexicality": 0,
      "count": 119,
      "word": "Guaynabo"
    },
    {
      "lexicality": 0,
      "count": 119,
      "word": "klatches"
    },
    {
      "lexicality": 0,
      "count": 119,
      "word": "kumbayah"
    },
    {
      "lexicality": 0,
      "count": 119,
      "word": "speargun"
    },
    {
      "lexicality": 0,
      "count": 119,
      "word": "penality"
    },
    {
      "lexicality": 0,
      "count": 119,
      "word": "canniest"
    },
    {
      "lexicality": 0,
      "count": 119,
      "word": "bankside"
    },
    {
      "lexicality": 0,
      "count": 119,
      "word": "overacts"
    },
    {
      "lexicality": 0,
      "count": 119,
      "word": "scantron"
    },
    {
      "lexicality": 0,
      "count": 119,
      "word": "Ulan-Ude"
    },
    {
      "lexicality": 0,
      "count": 119,
      "word": "Nevisian"
    },
    {
      "lexicality": 0,
      "count": 119,
      "word": "Cal Tech"
    },
    {
      "lexicality": 0,
      "count": 119,
      "word": "Titanian"
    },
    {
      "lexicality": 0,
      "count": 119,
      "word": "filmland"
    },
    {
      "lexicality": 0,
      "count": 119,
      "word": "tasklist"
    },
    {
      "lexicality": 0,
      "count": 118,
      "word": "enchased"
    },
    {
      "lexicality": 0,
      "count": 118,
      "word": "a-tiptoe"
    },
    {
      "lexicality": 0,
      "count": 118,
      "word": "Susheela"
    },
    {
      "lexicality": 0,
      "count": 118,
      "word": "carraway"
    },
    {
      "lexicality": 0,
      "count": 118,
      "word": "cracklin"
    },
    {
      "lexicality": 0,
      "count": 118,
      "word": "vaporise"
    },
    {
      "lexicality": 0,
      "count": 118,
      "word": "airdates"
    },
    {
      "lexicality": 0,
      "count": 118,
      "word": "holdalls"
    },
    {
      "lexicality": 0,
      "count": 118,
      "word": "Monachus"
    },
    {
      "lexicality": 0,
      "count": 118,
      "word": "gaveling"
    },
    {
      "lexicality": 0,
      "count": 118,
      "word": "Norrland"
    },
    {
      "lexicality": 0,
      "count": 118,
      "word": "misusage"
    },
    {
      "lexicality": 0,
      "count": 118,
      "word": "mahimahi"
    },
    {
      "lexicality": 0,
      "count": 118,
      "word": "saguaros"
    },
    {
      "lexicality": 0,
      "count": 118,
      "word": "dolmades"
    },
    {
      "lexicality": 0,
      "count": 118,
      "word": "Mary Sue"
    },
    {
      "lexicality": 0,
      "count": 117,
      "word": "scenical"
    },
    {
      "lexicality": 0,
      "count": 117,
      "word": "alluvion"
    },
    {
      "lexicality": 0,
      "count": 117,
      "word": "allodial"
    },
    {
      "lexicality": 0,
      "count": 117,
      "word": "awakener"
    },
    {
      "lexicality": 0,
      "count": 117,
      "word": "chagrins"
    },
    {
      "lexicality": 0,
      "count": 117,
      "word": "lunation"
    },
    {
      "lexicality": 0,
      "count": 117,
      "word": "diabolus"
    },
    {
      "lexicality": 0,
      "count": 117,
      "word": "mossback"
    },
    {
      "lexicality": 0,
      "count": 117,
      "word": "thiazide"
    },
    {
      "lexicality": 0,
      "count": 117,
      "word": "chanteys"
    },
    {
      "lexicality": 0,
      "count": 117,
      "word": "Ottawans"
    },
    {
      "lexicality": 0,
      "count": 117,
      "word": "seepages"
    },
    {
      "lexicality": 0,
      "count": 117,
      "word": "bear-pit"
    },
    {
      "lexicality": 0,
      "count": 117,
      "word": "jugulars"
    },
    {
      "lexicality": 0,
      "count": 117,
      "word": "bannable"
    },
    {
      "lexicality": 0,
      "count": 117,
      "word": "Cycladic"
    },
    {
      "lexicality": 0,
      "count": 117,
      "word": "feijoada"
    },
    {
      "lexicality": 0,
      "count": 117,
      "word": "whitehat"
    },
    {
      "lexicality": 0,
      "count": 116,
      "word": "cartouch"
    },
    {
      "lexicality": 0,
      "count": 116,
      "word": "avaritia"
    },
    {
      "lexicality": 0,
      "count": 116,
      "word": "apodosis"
    },
    {
      "lexicality": 0,
      "count": 116,
      "word": "Cunarder"
    },
    {
      "lexicality": 0,
      "count": 116,
      "word": "alembics"
    },
    {
      "lexicality": 0,
      "count": 116,
      "word": "Svizzera"
    },
    {
      "lexicality": 0,
      "count": 116,
      "word": "jackoffs"
    },
    {
      "lexicality": 0,
      "count": 116,
      "word": "collegia"
    },
    {
      "lexicality": 0,
      "count": 116,
      "word": "headling"
    },
    {
      "lexicality": 0,
      "count": 116,
      "word": "derivate"
    },
    {
      "lexicality": 0,
      "count": 116,
      "word": "wreathen"
    },
    {
      "lexicality": 0,
      "count": 116,
      "word": "Arabized"
    },
    {
      "lexicality": 0,
      "count": 116,
      "word": "chattily"
    },
    {
      "lexicality": 0,
      "count": 116,
      "word": "sideband"
    },
    {
      "lexicality": 0,
      "count": 116,
      "word": "polestar"
    },
    {
      "lexicality": 0,
      "count": 116,
      "word": "bookbags"
    },
    {
      "lexicality": 0,
      "count": 116,
      "word": "agonises"
    },
    {
      "lexicality": 0,
      "count": 116,
      "word": "panoptic"
    },
    {
      "lexicality": 0,
      "count": 116,
      "word": "pattypan"
    },
    {
      "lexicality": 0,
      "count": 116,
      "word": "Naxcivan"
    },
    {
      "lexicality": 0,
      "count": 115,
      "word": "sillable"
    },
    {
      "lexicality": 0,
      "count": 115,
      "word": "hackneys"
    },
    {
      "lexicality": 0,
      "count": 115,
      "word": "qualmish"
    },
    {
      "lexicality": 0,
      "count": 115,
      "word": "Aceldama"
    },
    {
      "lexicality": 0,
      "count": 115,
      "word": "amidship"
    },
    {
      "lexicality": 0,
      "count": 115,
      "word": "amplexus"
    },
    {
      "lexicality": 0,
      "count": 115,
      "word": "formable"
    },
    {
      "lexicality": 0,
      "count": 115,
      "word": "co-actor"
    },
    {
      "lexicality": 0,
      "count": 115,
      "word": "fantails"
    },
    {
      "lexicality": 0,
      "count": 115,
      "word": "far-gone"
    },
    {
      "lexicality": 0,
      "count": 115,
      "word": "Laetrile"
    },
    {
      "lexicality": 0,
      "count": 115,
      "word": "lashless"
    },
    {
      "lexicality": 0,
      "count": 115,
      "word": "valorize"
    },
    {
      "lexicality": 0,
      "count": 115,
      "word": "asterism"
    },
    {
      "lexicality": 0,
      "count": 115,
      "word": "rotaries"
    },
    {
      "lexicality": 0,
      "count": 115,
      "word": "beanball"
    },
    {
      "lexicality": 0,
      "count": 115,
      "word": "paperbag"
    },
    {
      "lexicality": 0,
      "count": 115,
      "word": "linalool"
    },
    {
      "lexicality": 0,
      "count": 115,
      "word": "gravitic"
    },
    {
      "lexicality": 0,
      "count": 115,
      "word": "muscaria"
    },
    {
      "lexicality": 0,
      "count": 115,
      "word": "snowcaps"
    },
    {
      "lexicality": 0,
      "count": 114,
      "word": "straucht"
    },
    {
      "lexicality": 0,
      "count": 114,
      "word": "air-line"
    },
    {
      "lexicality": 0,
      "count": 114,
      "word": "waysides"
    },
    {
      "lexicality": 0,
      "count": 114,
      "word": "halliard"
    },
    {
      "lexicality": 0,
      "count": 114,
      "word": "domainer"
    },
    {
      "lexicality": 0,
      "count": 114,
      "word": "flanging"
    },
    {
      "lexicality": 0,
      "count": 114,
      "word": "tramline"
    },
    {
      "lexicality": 0,
      "count": 114,
      "word": "Hispanos"
    },
    {
      "lexicality": 0,
      "count": 114,
      "word": "labelers"
    },
    {
      "lexicality": 0,
      "count": 114,
      "word": "carotids"
    },
    {
      "lexicality": 0,
      "count": 114,
      "word": "aggrieve"
    },
    {
      "lexicality": 0,
      "count": 114,
      "word": "kidswear"
    },
    {
      "lexicality": 0,
      "count": 114,
      "word": "Romansch"
    },
    {
      "lexicality": 0,
      "count": 114,
      "word": "evitable"
    },
    {
      "lexicality": 0,
      "count": 114,
      "word": "primulas"
    },
    {
      "lexicality": 0,
      "count": 114,
      "word": "internat"
    },
    {
      "lexicality": 0,
      "count": 114,
      "word": "gnashers"
    },
    {
      "lexicality": 0,
      "count": 114,
      "word": "Kosovans"
    },
    {
      "lexicality": 0,
      "count": 114,
      "word": "hateable"
    },
    {
      "lexicality": 0,
      "count": 114,
      "word": "play-act"
    },
    {
      "lexicality": 0,
      "count": 114,
      "word": "non-goal"
    },
    {
      "lexicality": 0,
      "count": 114,
      "word": "pissants"
    },
    {
      "lexicality": 0,
      "count": 114,
      "word": "salvager"
    },
    {
      "lexicality": 0,
      "count": 114,
      "word": "behalves"
    },
    {
      "lexicality": 0,
      "count": 114,
      "word": "pixelate"
    },
    {
      "lexicality": 0,
      "count": 113,
      "word": "callants"
    },
    {
      "lexicality": 0,
      "count": 113,
      "word": "naphthol"
    },
    {
      "lexicality": 0,
      "count": 113,
      "word": "accuseth"
    },
    {
      "lexicality": 0,
      "count": 113,
      "word": "charsets"
    },
    {
      "lexicality": 0,
      "count": 113,
      "word": "carouses"
    },
    {
      "lexicality": 0,
      "count": 113,
      "word": "wettable"
    },
    {
      "lexicality": 0,
      "count": 113,
      "word": "bloaters"
    },
    {
      "lexicality": 0,
      "count": 113,
      "word": "tragedie"
    },
    {
      "lexicality": 0,
      "count": 113,
      "word": "Oceanian"
    },
    {
      "lexicality": 0,
      "count": 113,
      "word": "arrestor"
    },
    {
      "lexicality": 0,
      "count": 113,
      "word": "megabuck"
    },
    {
      "lexicality": 0,
      "count": 113,
      "word": "pastille"
    },
    {
      "lexicality": 0,
      "count": 113,
      "word": "iced-tea"
    },
    {
      "lexicality": 0,
      "count": 113,
      "word": "basepath"
    },
    {
      "lexicality": 0,
      "count": 113,
      "word": "ballcaps"
    },
    {
      "lexicality": 0,
      "count": 113,
      "word": "Smithian"
    },
    {
      "lexicality": 0,
      "count": 113,
      "word": "deglazed"
    },
    {
      "lexicality": 0,
      "count": 112,
      "word": "britchka"
    },
    {
      "lexicality": 0,
      "count": 112,
      "word": "risaldar"
    },
    {
      "lexicality": 0,
      "count": 112,
      "word": "toll-bar"
    },
    {
      "lexicality": 0,
      "count": 112,
      "word": "langsyne"
    },
    {
      "lexicality": 0,
      "count": 112,
      "word": "miasmata"
    },
    {
      "lexicality": 0,
      "count": 112,
      "word": "dividual"
    },
    {
      "lexicality": 0,
      "count": 112,
      "word": "centaury"
    },
    {
      "lexicality": 0,
      "count": 112,
      "word": "panpipes"
    },
    {
      "lexicality": 0,
      "count": 112,
      "word": "shoptalk"
    },
    {
      "lexicality": 0,
      "count": 112,
      "word": "maggiore"
    },
    {
      "lexicality": 0,
      "count": 112,
      "word": "ducktail"
    },
    {
      "lexicality": 0,
      "count": 112,
      "word": "dayslong"
    },
    {
      "lexicality": 0,
      "count": 112,
      "word": "manwhore"
    },
    {
      "lexicality": 0,
      "count": 112,
      "word": "handwave"
    },
    {
      "lexicality": 0,
      "count": 112,
      "word": "nonpolar"
    },
    {
      "lexicality": 0,
      "count": 111,
      "word": "Navajoes"
    },
    {
      "lexicality": 0,
      "count": 111,
      "word": "ice-wall"
    },
    {
      "lexicality": 0,
      "count": 111,
      "word": "nestable"
    },
    {
      "lexicality": 0,
      "count": 111,
      "word": "stannous"
    },
    {
      "lexicality": 0,
      "count": 111,
      "word": "bondmaid"
    },
    {
      "lexicality": 0,
      "count": 111,
      "word": "abscissa"
    },
    {
      "lexicality": 0,
      "count": 111,
      "word": "Rastaman"
    },
    {
      "lexicality": 0,
      "count": 111,
      "word": "rotators"
    },
    {
      "lexicality": 0,
      "count": 111,
      "word": "magnetar"
    },
    {
      "lexicality": 0,
      "count": 111,
      "word": "midmajor"
    },
    {
      "lexicality": 0,
      "count": 111,
      "word": "fraulein"
    },
    {
      "lexicality": 0,
      "count": 111,
      "word": "tarsiers"
    },
    {
      "lexicality": 0,
      "count": 111,
      "word": "atremble"
    },
    {
      "lexicality": 0,
      "count": 111,
      "word": "apporter"
    },
    {
      "lexicality": 0,
      "count": 111,
      "word": "moneybag"
    },
    {
      "lexicality": 0,
      "count": 111,
      "word": "misalign"
    },
    {
      "lexicality": 0,
      "count": 111,
      "word": "cockapoo"
    },
    {
      "lexicality": 0,
      "count": 111,
      "word": "paste-up"
    },
    {
      "lexicality": 0,
      "count": 111,
      "word": "whammies"
    },
    {
      "lexicality": 0,
      "count": 111,
      "word": "foofaraw"
    },
    {
      "lexicality": 0,
      "count": 111,
      "word": "buddleia"
    },
    {
      "lexicality": 0,
      "count": 110,
      "word": "Macrorie"
    },
    {
      "lexicality": 0,
      "count": 110,
      "word": "millages"
    },
    {
      "lexicality": 0,
      "count": 110,
      "word": "slangily"
    },
    {
      "lexicality": 0,
      "count": 110,
      "word": "tapsters"
    },
    {
      "lexicality": 0,
      "count": 110,
      "word": "plagiary"
    },
    {
      "lexicality": 0,
      "count": 110,
      "word": "chelator"
    },
    {
      "lexicality": 0,
      "count": 110,
      "word": "outrance"
    },
    {
      "lexicality": 0,
      "count": 110,
      "word": "decayeth"
    },
    {
      "lexicality": 0,
      "count": 110,
      "word": "Halamish"
    },
    {
      "lexicality": 0,
      "count": 110,
      "word": "chimaera"
    },
    {
      "lexicality": 0,
      "count": 110,
      "word": "Pascendi"
    },
    {
      "lexicality": 0,
      "count": 110,
      "word": "toadyism"
    },
    {
      "lexicality": 0,
      "count": 110,
      "word": "unallied"
    },
    {
      "lexicality": 0,
      "count": 110,
      "word": "thatches"
    },
    {
      "lexicality": 0,
      "count": 110,
      "word": "subgrade"
    },
    {
      "lexicality": 0,
      "count": 110,
      "word": "partyism"
    },
    {
      "lexicality": 0,
      "count": 110,
      "word": "diaconal"
    },
    {
      "lexicality": 0,
      "count": 110,
      "word": "outcaste"
    },
    {
      "lexicality": 0,
      "count": 110,
      "word": "washdown"
    },
    {
      "lexicality": 0,
      "count": 110,
      "word": "backbend"
    },
    {
      "lexicality": 0,
      "count": 110,
      "word": "omphalos"
    },
    {
      "lexicality": 0,
      "count": 110,
      "word": "fellated"
    },
    {
      "lexicality": 0,
      "count": 110,
      "word": "smartens"
    },
    {
      "lexicality": 0,
      "count": 109,
      "word": "cityward"
    },
    {
      "lexicality": 0,
      "count": 109,
      "word": "coal-box"
    },
    {
      "lexicality": 0,
      "count": 109,
      "word": "mondaine"
    },
    {
      "lexicality": 0,
      "count": 109,
      "word": "carryons"
    },
    {
      "lexicality": 0,
      "count": 109,
      "word": "Sangallo"
    },
    {
      "lexicality": 0,
      "count": 109,
      "word": "expiates"
    },
    {
      "lexicality": 0,
      "count": 109,
      "word": "damasked"
    },
    {
      "lexicality": 0,
      "count": 109,
      "word": "maildrop"
    },
    {
      "lexicality": 0,
      "count": 109,
      "word": "aguacate"
    },
    {
      "lexicality": 0,
      "count": 109,
      "word": "muleback"
    },
    {
      "lexicality": 0,
      "count": 109,
      "word": "Cagney's"
    },
    {
      "lexicality": 0,
      "count": 109,
      "word": "ballocks"
    },
    {
      "lexicality": 0,
      "count": 109,
      "word": "oxalates"
    },
    {
      "lexicality": 0,
      "count": 109,
      "word": "brashest"
    },
    {
      "lexicality": 0,
      "count": 109,
      "word": "gematria"
    },
    {
      "lexicality": 0,
      "count": 109,
      "word": "unbathed"
    },
    {
      "lexicality": 0,
      "count": 109,
      "word": "valences"
    },
    {
      "lexicality": 0,
      "count": 109,
      "word": "shaggier"
    },
    {
      "lexicality": 0,
      "count": 109,
      "word": "Amchitka"
    },
    {
      "lexicality": 0,
      "count": 109,
      "word": "rotundas"
    },
    {
      "lexicality": 0,
      "count": 109,
      "word": "unstaged"
    },
    {
      "lexicality": 0,
      "count": 108,
      "word": "Branting"
    },
    {
      "lexicality": 0,
      "count": 108,
      "word": "ruinated"
    },
    {
      "lexicality": 0,
      "count": 108,
      "word": "aculeata"
    },
    {
      "lexicality": 0,
      "count": 108,
      "word": "mamaliga"
    },
    {
      "lexicality": 0,
      "count": 108,
      "word": "Djakarta"
    },
    {
      "lexicality": 0,
      "count": 108,
      "word": "retarget"
    },
    {
      "lexicality": 0,
      "count": 108,
      "word": "scabious"
    },
    {
      "lexicality": 0,
      "count": 108,
      "word": "cryostat"
    },
    {
      "lexicality": 0,
      "count": 108,
      "word": "T-square"
    },
    {
      "lexicality": 0,
      "count": 108,
      "word": "Togarmah"
    },
    {
      "lexicality": 0,
      "count": 108,
      "word": "tyrannus"
    },
    {
      "lexicality": 0,
      "count": 108,
      "word": "farmable"
    },
    {
      "lexicality": 0,
      "count": 108,
      "word": "ballsack"
    },
    {
      "lexicality": 0,
      "count": 108,
      "word": "jerkface"
    },
    {
      "lexicality": 0,
      "count": 108,
      "word": "yachters"
    },
    {
      "lexicality": 0,
      "count": 108,
      "word": "collabos"
    },
    {
      "lexicality": 0,
      "count": 108,
      "word": "amnestic"
    },
    {
      "lexicality": 0,
      "count": 108,
      "word": "mangabey"
    },
    {
      "lexicality": 0,
      "count": 108,
      "word": "phalange"
    },
    {
      "lexicality": 0,
      "count": 108,
      "word": "laconica"
    },
    {
      "lexicality": 0,
      "count": 108,
      "word": "ambrette"
    },
    {
      "lexicality": 0,
      "count": 107,
      "word": "vagabone"
    },
    {
      "lexicality": 0,
      "count": 107,
      "word": "pipeclay"
    },
    {
      "lexicality": 0,
      "count": 107,
      "word": "hillsman"
    },
    {
      "lexicality": 0,
      "count": 107,
      "word": "Jhingade"
    },
    {
      "lexicality": 0,
      "count": 107,
      "word": "ravelins"
    },
    {
      "lexicality": 0,
      "count": 107,
      "word": "masonary"
    },
    {
      "lexicality": 0,
      "count": 107,
      "word": "sea-worn"
    },
    {
      "lexicality": 0,
      "count": 107,
      "word": "spatting"
    },
    {
      "lexicality": 0,
      "count": 107,
      "word": "arrestin"
    },
    {
      "lexicality": 0,
      "count": 107,
      "word": "vanpools"
    },
    {
      "lexicality": 0,
      "count": 107,
      "word": "pass-out"
    },
    {
      "lexicality": 0,
      "count": 107,
      "word": "pot-head"
    },
    {
      "lexicality": 0,
      "count": 107,
      "word": "tangoing"
    },
    {
      "lexicality": 0,
      "count": 107,
      "word": "patronal"
    },
    {
      "lexicality": 0,
      "count": 107,
      "word": "obeisant"
    },
    {
      "lexicality": 0,
      "count": 107,
      "word": "orgasmed"
    },
    {
      "lexicality": 0,
      "count": 107,
      "word": "brawnier"
    },
    {
      "lexicality": 0,
      "count": 107,
      "word": "kreplach"
    },
    {
      "lexicality": 0,
      "count": 107,
      "word": "intarweb"
    },
    {
      "lexicality": 0,
      "count": 106,
      "word": "asphalte"
    },
    {
      "lexicality": 0,
      "count": 106,
      "word": "aeriform"
    },
    {
      "lexicality": 0,
      "count": 106,
      "word": "assayers"
    },
    {
      "lexicality": 0,
      "count": 106,
      "word": "chaldron"
    },
    {
      "lexicality": 0,
      "count": 106,
      "word": "explants"
    },
    {
      "lexicality": 0,
      "count": 106,
      "word": "meat-pie"
    },
    {
      "lexicality": 0,
      "count": 106,
      "word": "Dena'ina"
    },
    {
      "lexicality": 0,
      "count": 106,
      "word": "cabstand"
    },
    {
      "lexicality": 0,
      "count": 106,
      "word": "labellum"
    },
    {
      "lexicality": 0,
      "count": 106,
      "word": "mateless"
    },
    {
      "lexicality": 0,
      "count": 106,
      "word": "Paulists"
    },
    {
      "lexicality": 0,
      "count": 106,
      "word": "comptant"
    },
    {
      "lexicality": 0,
      "count": 106,
      "word": "lamblike"
    },
    {
      "lexicality": 0,
      "count": 106,
      "word": "Nakhodka"
    },
    {
      "lexicality": 0,
      "count": 106,
      "word": "Solidago"
    },
    {
      "lexicality": 0,
      "count": 106,
      "word": "lakebeds"
    },
    {
      "lexicality": 0,
      "count": 106,
      "word": "digraphs"
    },
    {
      "lexicality": 0,
      "count": 106,
      "word": "simulant"
    },
    {
      "lexicality": 0,
      "count": 106,
      "word": "beasting"
    },
    {
      "lexicality": 0,
      "count": 106,
      "word": "lay-down"
    },
    {
      "lexicality": 0,
      "count": 106,
      "word": "relators"
    },
    {
      "lexicality": 0,
      "count": 106,
      "word": "gazumped"
    },
    {
      "lexicality": 0,
      "count": 106,
      "word": "megamall"
    },
    {
      "lexicality": 0,
      "count": 106,
      "word": "suck-ass"
    },
    {
      "lexicality": 0,
      "count": 106,
      "word": "mudflaps"
    },
    {
      "lexicality": 0,
      "count": 106,
      "word": "ballboys"
    },
    {
      "lexicality": 0,
      "count": 106,
      "word": "bilabial"
    },
    {
      "lexicality": 0,
      "count": 105,
      "word": "dalesmen"
    },
    {
      "lexicality": 0,
      "count": 105,
      "word": "tofranil"
    },
    {
      "lexicality": 0,
      "count": 105,
      "word": "brahmans"
    },
    {
      "lexicality": 0,
      "count": 105,
      "word": "handpump"
    },
    {
      "lexicality": 0,
      "count": 105,
      "word": "loxapine"
    },
    {
      "lexicality": 0,
      "count": 105,
      "word": "quantize"
    },
    {
      "lexicality": 0,
      "count": 105,
      "word": "bikeable"
    },
    {
      "lexicality": 0,
      "count": 105,
      "word": "sangomas"
    },
    {
      "lexicality": 0,
      "count": 105,
      "word": "headwork"
    },
    {
      "lexicality": 0,
      "count": 105,
      "word": "rat-tail"
    },
    {
      "lexicality": 0,
      "count": 105,
      "word": "raveling"
    },
    {
      "lexicality": 0,
      "count": 105,
      "word": "handsaws"
    },
    {
      "lexicality": 0,
      "count": 105,
      "word": "descanso"
    },
    {
      "lexicality": 0,
      "count": 105,
      "word": "Manannan"
    },
    {
      "lexicality": 0,
      "count": 105,
      "word": "vocalese"
    },
    {
      "lexicality": 0,
      "count": 105,
      "word": "lollygag"
    },
    {
      "lexicality": 0,
      "count": 105,
      "word": "topcoats"
    },
    {
      "lexicality": 0,
      "count": 105,
      "word": "uprating"
    },
    {
      "lexicality": 0,
      "count": 105,
      "word": "walkmans"
    },
    {
      "lexicality": 0,
      "count": 105,
      "word": "palazzos"
    },
    {
      "lexicality": 0,
      "count": 105,
      "word": "fruitbat"
    },
    {
      "lexicality": 0,
      "count": 105,
      "word": "Baby Doc"
    },
    {
      "lexicality": 0,
      "count": 105,
      "word": "La Plata"
    },
    {
      "lexicality": 0,
      "count": 104,
      "word": "far-seen"
    },
    {
      "lexicality": 0,
      "count": 104,
      "word": "homeloan"
    },
    {
      "lexicality": 0,
      "count": 104,
      "word": "basileus"
    },
    {
      "lexicality": 0,
      "count": 104,
      "word": "Romanova"
    },
    {
      "lexicality": 0,
      "count": 104,
      "word": "faultily"
    },
    {
      "lexicality": 0,
      "count": 104,
      "word": "aureoles"
    },
    {
      "lexicality": 0,
      "count": 104,
      "word": "ash-gray"
    },
    {
      "lexicality": 0,
      "count": 104,
      "word": "Stenmark"
    },
    {
      "lexicality": 0,
      "count": 104,
      "word": "retaught"
    },
    {
      "lexicality": 0,
      "count": 104,
      "word": "lawbooks"
    },
    {
      "lexicality": 0,
      "count": 104,
      "word": "spalling"
    },
    {
      "lexicality": 0,
      "count": 104,
      "word": "dashikis"
    },
    {
      "lexicality": 0,
      "count": 104,
      "word": "arrivers"
    },
    {
      "lexicality": 0,
      "count": 104,
      "word": "halachah"
    },
    {
      "lexicality": 0,
      "count": 104,
      "word": "Natufian"
    },
    {
      "lexicality": 0,
      "count": 104,
      "word": "patchier"
    },
    {
      "lexicality": 0,
      "count": 104,
      "word": "lantanas"
    },
    {
      "lexicality": 0,
      "count": 103,
      "word": "Martaban"
    },
    {
      "lexicality": 0,
      "count": 103,
      "word": "saw-like"
    },
    {
      "lexicality": 0,
      "count": 103,
      "word": "awfulest"
    },
    {
      "lexicality": 0,
      "count": 103,
      "word": "Zairians"
    },
    {
      "lexicality": 0,
      "count": 103,
      "word": "flatties"
    },
    {
      "lexicality": 0,
      "count": 103,
      "word": "highpass"
    },
    {
      "lexicality": 0,
      "count": 103,
      "word": "Enewetak"
    },
    {
      "lexicality": 0,
      "count": 103,
      "word": "calledst"
    },
    {
      "lexicality": 0,
      "count": 103,
      "word": "Stanicky"
    },
    {
      "lexicality": 0,
      "count": 103,
      "word": "changest"
    },
    {
      "lexicality": 0,
      "count": 103,
      "word": "capitata"
    },
    {
      "lexicality": 0,
      "count": 103,
      "word": "ramipril"
    },
    {
      "lexicality": 0,
      "count": 103,
      "word": "subpanel"
    },
    {
      "lexicality": 0,
      "count": 103,
      "word": "tabloidy"
    },
    {
      "lexicality": 0,
      "count": 103,
      "word": "satphone"
    },
    {
      "lexicality": 0,
      "count": 103,
      "word": "backchat"
    },
    {
      "lexicality": 0,
      "count": 103,
      "word": "rightard"
    },
    {
      "lexicality": 0,
      "count": 103,
      "word": "smarmily"
    },
    {
      "lexicality": 0,
      "count": 103,
      "word": "ant-lion"
    },
    {
      "lexicality": 0,
      "count": 103,
      "word": "midscale"
    },
    {
      "lexicality": 0,
      "count": 103,
      "word": "goshawks"
    },
    {
      "lexicality": 0,
      "count": 103,
      "word": "Havdalah"
    },
    {
      "lexicality": 0,
      "count": 103,
      "word": "callaloo"
    },
    {
      "lexicality": 0,
      "count": 103,
      "word": "firetrap"
    },
    {
      "lexicality": 0,
      "count": 103,
      "word": "sackable"
    },
    {
      "lexicality": 0,
      "count": 103,
      "word": "Juventas"
    },
    {
      "lexicality": 0,
      "count": 102,
      "word": "maravedi"
    },
    {
      "lexicality": 0,
      "count": 102,
      "word": "sea-cook"
    },
    {
      "lexicality": 0,
      "count": 102,
      "word": "Polygala"
    },
    {
      "lexicality": 0,
      "count": 102,
      "word": "carbaryl"
    },
    {
      "lexicality": 0,
      "count": 102,
      "word": "myoblast"
    },
    {
      "lexicality": 0,
      "count": 102,
      "word": "sick-bay"
    },
    {
      "lexicality": 0,
      "count": 102,
      "word": "viatical"
    },
    {
      "lexicality": 0,
      "count": 102,
      "word": "Yinchuan"
    },
    {
      "lexicality": 0,
      "count": 102,
      "word": "hand-gun"
    },
    {
      "lexicality": 0,
      "count": 102,
      "word": "asserter"
    },
    {
      "lexicality": 0,
      "count": 102,
      "word": "cantrips"
    },
    {
      "lexicality": 0,
      "count": 102,
      "word": "goalward"
    },
    {
      "lexicality": 0,
      "count": 102,
      "word": "arcadian"
    },
    {
      "lexicality": 0,
      "count": 102,
      "word": "Lamanite"
    },
    {
      "lexicality": 0,
      "count": 102,
      "word": "maltitol"
    },
    {
      "lexicality": 0,
      "count": 102,
      "word": "hemostat"
    },
    {
      "lexicality": 0,
      "count": 102,
      "word": "peacably"
    },
    {
      "lexicality": 0,
      "count": 102,
      "word": "headiest"
    },
    {
      "lexicality": 0,
      "count": 102,
      "word": "clackety"
    },
    {
      "lexicality": 0,
      "count": 102,
      "word": "grandads"
    },
    {
      "lexicality": 0,
      "count": 102,
      "word": "dishrags"
    },
    {
      "lexicality": 0,
      "count": 102,
      "word": "panfried"
    },
    {
      "lexicality": 0,
      "count": 102,
      "word": "wankfest"
    },
    {
      "lexicality": 0,
      "count": 102,
      "word": "transman"
    },
    {
      "lexicality": 0,
      "count": 102,
      "word": "skeeball"
    },
    {
      "lexicality": 0,
      "count": 101,
      "word": "lap-robe"
    },
    {
      "lexicality": 0,
      "count": 101,
      "word": "patteran"
    },
    {
      "lexicality": 0,
      "count": 101,
      "word": "chamfers"
    },
    {
      "lexicality": 0,
      "count": 101,
      "word": "varietas"
    },
    {
      "lexicality": 0,
      "count": 101,
      "word": "superbia"
    },
    {
      "lexicality": 0,
      "count": 101,
      "word": "bandsaws"
    },
    {
      "lexicality": 0,
      "count": 101,
      "word": "polynyas"
    },
    {
      "lexicality": 0,
      "count": 101,
      "word": "patroons"
    },
    {
      "lexicality": 0,
      "count": 101,
      "word": "farouche"
    },
    {
      "lexicality": 0,
      "count": 101,
      "word": "quatorze"
    },
    {
      "lexicality": 0,
      "count": 101,
      "word": "sandpile"
    },
    {
      "lexicality": 0,
      "count": 101,
      "word": "charette"
    },
    {
      "lexicality": 0,
      "count": 101,
      "word": "balmiest"
    },
    {
      "lexicality": 0,
      "count": 101,
      "word": "clavinet"
    },
    {
      "lexicality": 0,
      "count": 101,
      "word": "jim-jams"
    },
    {
      "lexicality": 0,
      "count": 101,
      "word": "begorrah"
    },
    {
      "lexicality": 0,
      "count": 101,
      "word": "smokable"
    },
    {
      "lexicality": 0,
      "count": 101,
      "word": "undammed"
    },
    {
      "lexicality": 0,
      "count": 101,
      "word": "accretes"
    },
    {
      "lexicality": 0,
      "count": 101,
      "word": "gabfests"
    },
    {
      "lexicality": 0,
      "count": 101,
      "word": "backslap"
    },
    {
      "lexicality": 0,
      "count": 101,
      "word": "weakfish"
    },
    {
      "lexicality": 0,
      "count": 101,
      "word": "cardizem"
    },
    {
      "lexicality": 0,
      "count": 101,
      "word": "klansman"
    },
    {
      "lexicality": 0,
      "count": 101,
      "word": "coatroom"
    },
    {
      "lexicality": 0,
      "count": 101,
      "word": "barbules"
    },
    {
      "lexicality": 0,
      "count": 101,
      "word": "paystubs"
    },
    {
      "lexicality": 0,
      "count": 100,
      "word": "up-train"
    },
    {
      "lexicality": 0,
      "count": 100,
      "word": "ratables"
    },
    {
      "lexicality": 0,
      "count": 100,
      "word": "Gallegan"
    },
    {
      "lexicality": 0,
      "count": 100,
      "word": "Nazimova"
    },
    {
      "lexicality": 0,
      "count": 100,
      "word": "tarriest"
    },
    {
      "lexicality": 0,
      "count": 100,
      "word": "rhizobia"
    },
    {
      "lexicality": 0,
      "count": 100,
      "word": "Bignonia"
    },
    {
      "lexicality": 0,
      "count": 100,
      "word": "Elisheba"
    },
    {
      "lexicality": 0,
      "count": 100,
      "word": "sexuales"
    },
    {
      "lexicality": 0,
      "count": 100,
      "word": "Takasaki"
    },
    {
      "lexicality": 0,
      "count": 100,
      "word": "scanline"
    },
    {
      "lexicality": 0,
      "count": 100,
      "word": "hearsays"
    },
    {
      "lexicality": 0,
      "count": 100,
      "word": "Archaean"
    },
    {
      "lexicality": 0,
      "count": 100,
      "word": "gyratory"
    },
    {
      "lexicality": 0,
      "count": 100,
      "word": "defatted"
    },
    {
      "lexicality": 0,
      "count": 100,
      "word": "cyanotic"
    },
    {
      "lexicality": 0,
      "count": 100,
      "word": "darknets"
    },
    {
      "lexicality": 0,
      "count": 100,
      "word": "assiette"
    },
    {
      "lexicality": 0,
      "count": 100,
      "word": "rhubarbs"
    },
    {
      "lexicality": 0,
      "count": 100,
      "word": "neatened"
    },
    {
      "lexicality": 0,
      "count": 100,
      "word": "raingear"
    },
    {
      "lexicality": 0,
      "count": 100,
      "word": "buzkashi"
    },
    {
      "lexicality": 0,
      "count": 99,
      "word": "ethnarch"
    },
    {
      "lexicality": 0,
      "count": 99,
      "word": "becamest"
    },
    {
      "lexicality": 0,
      "count": 99,
      "word": "narghile"
    },
    {
      "lexicality": 0,
      "count": 99,
      "word": "caspases"
    },
    {
      "lexicality": 0,
      "count": 99,
      "word": "capitula"
    },
    {
      "lexicality": 0,
      "count": 99,
      "word": "premolar"
    },
    {
      "lexicality": 0,
      "count": 99,
      "word": "crannied"
    },
    {
      "lexicality": 0,
      "count": 99,
      "word": "hardtops"
    },
    {
      "lexicality": 0,
      "count": 99,
      "word": "ironbark"
    },
    {
      "lexicality": 0,
      "count": 99,
      "word": "cremates"
    },
    {
      "lexicality": 0,
      "count": 99,
      "word": "fenestra"
    },
    {
      "lexicality": 0,
      "count": 99,
      "word": "Fascisti"
    },
    {
      "lexicality": 0,
      "count": 99,
      "word": "doolally"
    },
    {
      "lexicality": 0,
      "count": 99,
      "word": "hatstand"
    },
    {
      "lexicality": 0,
      "count": 99,
      "word": "grognard"
    },
    {
      "lexicality": 0,
      "count": 99,
      "word": "shaggers"
    },
    {
      "lexicality": 0,
      "count": 98,
      "word": "raspings"
    },
    {
      "lexicality": 0,
      "count": 98,
      "word": "demersal"
    },
    {
      "lexicality": 0,
      "count": 98,
      "word": "hollands"
    },
    {
      "lexicality": 0,
      "count": 98,
      "word": "lampless"
    },
    {
      "lexicality": 0,
      "count": 98,
      "word": "leg-bail"
    },
    {
      "lexicality": 0,
      "count": 98,
      "word": "canoness"
    },
    {
      "lexicality": 0,
      "count": 98,
      "word": "Borassus"
    },
    {
      "lexicality": 0,
      "count": 98,
      "word": "Danaides"
    },
    {
      "lexicality": 0,
      "count": 98,
      "word": "camgirls"
    },
    {
      "lexicality": 0,
      "count": 98,
      "word": "elastica"
    },
    {
      "lexicality": 0,
      "count": 98,
      "word": "myalgias"
    },
    {
      "lexicality": 0,
      "count": 98,
      "word": "blackies"
    },
    {
      "lexicality": 0,
      "count": 98,
      "word": "Chicanas"
    },
    {
      "lexicality": 0,
      "count": 98,
      "word": "dead-man"
    },
    {
      "lexicality": 0,
      "count": 98,
      "word": "headbang"
    },
    {
      "lexicality": 0,
      "count": 98,
      "word": "manouver"
    },
    {
      "lexicality": 0,
      "count": 98,
      "word": "lactones"
    },
    {
      "lexicality": 0,
      "count": 98,
      "word": "oarlocks"
    },
    {
      "lexicality": 0,
      "count": 98,
      "word": "traiteur"
    },
    {
      "lexicality": 0,
      "count": 98,
      "word": "cashable"
    },
    {
      "lexicality": 0,
      "count": 98,
      "word": "prebaked"
    },
    {
      "lexicality": 0,
      "count": 98,
      "word": "planchet"
    },
    {
      "lexicality": 0,
      "count": 98,
      "word": "waterski"
    },
    {
      "lexicality": 0,
      "count": 97,
      "word": "truckman"
    },
    {
      "lexicality": 0,
      "count": 97,
      "word": "sand-bed"
    },
    {
      "lexicality": 0,
      "count": 97,
      "word": "pantiles"
    },
    {
      "lexicality": 0,
      "count": 97,
      "word": "salt-box"
    },
    {
      "lexicality": 0,
      "count": 97,
      "word": "legatura"
    },
    {
      "lexicality": 0,
      "count": 97,
      "word": "bindable"
    },
    {
      "lexicality": 0,
      "count": 97,
      "word": "ditambah"
    },
    {
      "lexicality": 0,
      "count": 97,
      "word": "Lilianna"
    },
    {
      "lexicality": 0,
      "count": 97,
      "word": "Perugian"
    },
    {
      "lexicality": 0,
      "count": 97,
      "word": "cascabel"
    },
    {
      "lexicality": 0,
      "count": 97,
      "word": "hoaxster"
    },
    {
      "lexicality": 0,
      "count": 97,
      "word": "analogic"
    },
    {
      "lexicality": 0,
      "count": 97,
      "word": "pull-tab"
    },
    {
      "lexicality": 0,
      "count": 97,
      "word": "ambulate"
    },
    {
      "lexicality": 0,
      "count": 97,
      "word": "bayesian"
    },
    {
      "lexicality": 0,
      "count": 97,
      "word": "Nataraja"
    },
    {
      "lexicality": 0,
      "count": 97,
      "word": "uncrated"
    },
    {
      "lexicality": 0,
      "count": 97,
      "word": "mandrels"
    },
    {
      "lexicality": 0,
      "count": 97,
      "word": "midwater"
    },
    {
      "lexicality": 0,
      "count": 97,
      "word": "Lilliana"
    },
    {
      "lexicality": 0,
      "count": 97,
      "word": "Badalona"
    },
    {
      "lexicality": 0,
      "count": 97,
      "word": "maypoles"
    },
    {
      "lexicality": 0,
      "count": 97,
      "word": "goombahs"
    },
    {
      "lexicality": 0,
      "count": 97,
      "word": "djellaba"
    },
    {
      "lexicality": 0,
      "count": 97,
      "word": "fishcake"
    },
    {
      "lexicality": 0,
      "count": 97,
      "word": "chaebols"
    },
    {
      "lexicality": 0,
      "count": 97,
      "word": "Raquelle"
    },
    {
      "lexicality": 0,
      "count": 97,
      "word": "rakehell"
    },
    {
      "lexicality": 0,
      "count": 97,
      "word": "chatbots"
    },
    {
      "lexicality": 0,
      "count": 96,
      "word": "sabbaton"
    },
    {
      "lexicality": 0,
      "count": 96,
      "word": "periagua"
    },
    {
      "lexicality": 0,
      "count": 96,
      "word": "finitary"
    },
    {
      "lexicality": 0,
      "count": 96,
      "word": "cystatin"
    },
    {
      "lexicality": 0,
      "count": 96,
      "word": "vitalise"
    },
    {
      "lexicality": 0,
      "count": 96,
      "word": "antisera"
    },
    {
      "lexicality": 0,
      "count": 96,
      "word": "mista'en"
    },
    {
      "lexicality": 0,
      "count": 96,
      "word": "zamindar"
    },
    {
      "lexicality": 0,
      "count": 96,
      "word": "unlearnt"
    },
    {
      "lexicality": 0,
      "count": 96,
      "word": "praisers"
    },
    {
      "lexicality": 0,
      "count": 96,
      "word": "Iraklion"
    },
    {
      "lexicality": 0,
      "count": 96,
      "word": "deceases"
    },
    {
      "lexicality": 0,
      "count": 96,
      "word": "marasmus"
    },
    {
      "lexicality": 0,
      "count": 96,
      "word": "diarised"
    },
    {
      "lexicality": 0,
      "count": 96,
      "word": "bug-bear"
    },
    {
      "lexicality": 0,
      "count": 96,
      "word": "portably"
    },
    {
      "lexicality": 0,
      "count": 96,
      "word": "ceramide"
    },
    {
      "lexicality": 0,
      "count": 96,
      "word": "alpinist"
    },
    {
      "lexicality": 0,
      "count": 96,
      "word": "waterers"
    },
    {
      "lexicality": 0,
      "count": 96,
      "word": "annelids"
    },
    {
      "lexicality": 0,
      "count": 96,
      "word": "peacoats"
    },
    {
      "lexicality": 0,
      "count": 96,
      "word": "archaeal"
    },
    {
      "lexicality": 0,
      "count": 96,
      "word": "towboats"
    },
    {
      "lexicality": 0,
      "count": 96,
      "word": "flabbier"
    },
    {
      "lexicality": 0,
      "count": 96,
      "word": "carnauba"
    },
    {
      "lexicality": 0,
      "count": 96,
      "word": "taproots"
    },
    {
      "lexicality": 0,
      "count": 96,
      "word": "regraded"
    },
    {
      "lexicality": 0,
      "count": 96,
      "word": "trilemma"
    },
    {
      "lexicality": 0,
      "count": 96,
      "word": "titrator"
    },
    {
      "lexicality": 0,
      "count": 96,
      "word": "Flagstad"
    },
    {
      "lexicality": 0,
      "count": 96,
      "word": "Rapa Nui"
    },
    {
      "lexicality": 0,
      "count": 96,
      "word": "largeish"
    },
    {
      "lexicality": 0,
      "count": 95,
      "word": "anchoret"
    },
    {
      "lexicality": 0,
      "count": 95,
      "word": "awanting"
    },
    {
      "lexicality": 0,
      "count": 95,
      "word": "carlines"
    },
    {
      "lexicality": 0,
      "count": 95,
      "word": "shaddock"
    },
    {
      "lexicality": 0,
      "count": 95,
      "word": "catechol"
    },
    {
      "lexicality": 0,
      "count": 95,
      "word": "bandeaux"
    },
    {
      "lexicality": 0,
      "count": 95,
      "word": "Hertzian"
    },
    {
      "lexicality": 0,
      "count": 95,
      "word": "Puebloan"
    },
    {
      "lexicality": 0,
      "count": 95,
      "word": "Udmurtia"
    },
    {
      "lexicality": 0,
      "count": 95,
      "word": "diatomic"
    },
    {
      "lexicality": 0,
      "count": 95,
      "word": "filarial"
    },
    {
      "lexicality": 0,
      "count": 95,
      "word": "aspected"
    },
    {
      "lexicality": 0,
      "count": 95,
      "word": "spankers"
    },
    {
      "lexicality": 0,
      "count": 95,
      "word": "fangless"
    },
    {
      "lexicality": 0,
      "count": 95,
      "word": "jarheads"
    },
    {
      "lexicality": 0,
      "count": 95,
      "word": "volaille"
    },
    {
      "lexicality": 0,
      "count": 95,
      "word": "rubrical"
    },
    {
      "lexicality": 0,
      "count": 95,
      "word": "nannyism"
    },
    {
      "lexicality": 0,
      "count": 95,
      "word": "mealworm"
    },
    {
      "lexicality": 0,
      "count": 95,
      "word": "crankily"
    },
    {
      "lexicality": 0,
      "count": 95,
      "word": "aureoled"
    },
    {
      "lexicality": 0,
      "count": 95,
      "word": "manpages"
    },
    {
      "lexicality": 0,
      "count": 94,
      "word": "Accadian"
    },
    {
      "lexicality": 0,
      "count": 94,
      "word": "megapode"
    },
    {
      "lexicality": 0,
      "count": 94,
      "word": "petaloid"
    },
    {
      "lexicality": 0,
      "count": 94,
      "word": "arsenite"
    },
    {
      "lexicality": 0,
      "count": 94,
      "word": "two-pair"
    },
    {
      "lexicality": 0,
      "count": 94,
      "word": "derating"
    },
    {
      "lexicality": 0,
      "count": 94,
      "word": "Lassie's"
    },
    {
      "lexicality": 0,
      "count": 94,
      "word": "jazzfest"
    },
    {
      "lexicality": 0,
      "count": 94,
      "word": "calliper"
    },
    {
      "lexicality": 0,
      "count": 94,
      "word": "brassard"
    },
    {
      "lexicality": 0,
      "count": 94,
      "word": "crevalle"
    },
    {
      "lexicality": 0,
      "count": 94,
      "word": "aquatint"
    },
    {
      "lexicality": 0,
      "count": 94,
      "word": "infarcts"
    },
    {
      "lexicality": 0,
      "count": 94,
      "word": "clawless"
    },
    {
      "lexicality": 0,
      "count": 94,
      "word": "saltfish"
    },
    {
      "lexicality": 0,
      "count": 94,
      "word": "endogamy"
    },
    {
      "lexicality": 0,
      "count": 94,
      "word": "unthawed"
    },
    {
      "lexicality": 0,
      "count": 94,
      "word": "sassiest"
    },
    {
      "lexicality": 0,
      "count": 94,
      "word": "artiness"
    },
    {
      "lexicality": 0,
      "count": 94,
      "word": "vacinity"
    },
    {
      "lexicality": 0,
      "count": 94,
      "word": "lifehack"
    },
    {
      "lexicality": 0,
      "count": 94,
      "word": "dazzlers"
    },
    {
      "lexicality": 0,
      "count": 93,
      "word": "carioles"
    },
    {
      "lexicality": 0,
      "count": 93,
      "word": "unwarmed"
    },
    {
      "lexicality": 0,
      "count": 93,
      "word": "aerolite"
    },
    {
      "lexicality": 0,
      "count": 93,
      "word": "ophidian"
    },
    {
      "lexicality": 0,
      "count": 93,
      "word": "botanize"
    },
    {
      "lexicality": 0,
      "count": 93,
      "word": "lobelias"
    },
    {
      "lexicality": 0,
      "count": 93,
      "word": "biasness"
    },
    {
      "lexicality": 0,
      "count": 93,
      "word": "ulcerate"
    },
    {
      "lexicality": 0,
      "count": 93,
      "word": "capicola"
    },
    {
      "lexicality": 0,
      "count": 93,
      "word": "caracara"
    },
    {
      "lexicality": 0,
      "count": 93,
      "word": "sporrans"
    },
    {
      "lexicality": 0,
      "count": 93,
      "word": "headhunt"
    },
    {
      "lexicality": 0,
      "count": 93,
      "word": "Ruisdael"
    },
    {
      "lexicality": 0,
      "count": 93,
      "word": "aerogels"
    },
    {
      "lexicality": 0,
      "count": 93,
      "word": "gateless"
    },
    {
      "lexicality": 0,
      "count": 93,
      "word": "subpolar"
    },
    {
      "lexicality": 0,
      "count": 93,
      "word": "mocktail"
    },
    {
      "lexicality": 0,
      "count": 93,
      "word": "chiasmus"
    },
    {
      "lexicality": 0,
      "count": 92,
      "word": "diarrhœa"
    },
    {
      "lexicality": 0,
      "count": 92,
      "word": "bedesman"
    },
    {
      "lexicality": 0,
      "count": 92,
      "word": "gala-day"
    },
    {
      "lexicality": 0,
      "count": 92,
      "word": "gallipot"
    },
    {
      "lexicality": 0,
      "count": 92,
      "word": "Vendidad"
    },
    {
      "lexicality": 0,
      "count": 92,
      "word": "earnests"
    },
    {
      "lexicality": 0,
      "count": 92,
      "word": "tea-cake"
    },
    {
      "lexicality": 0,
      "count": 92,
      "word": "marchese"
    },
    {
      "lexicality": 0,
      "count": 92,
      "word": "leaguing"
    },
    {
      "lexicality": 0,
      "count": 92,
      "word": "asthenic"
    },
    {
      "lexicality": 0,
      "count": 92,
      "word": "Mobilian"
    },
    {
      "lexicality": 0,
      "count": 92,
      "word": "cellaret"
    },
    {
      "lexicality": 0,
      "count": 92,
      "word": "milliamp"
    },
    {
      "lexicality": 0,
      "count": 92,
      "word": "aligners"
    }
  ]
}
